{
"creatingLibrary": {
"name": "MediaInfoLib",
"version": "23.04",
"url": "https://mediaarea.net/MediaInfo"
},
"media": {
"@ref": "/mnt/e/Movies/bili/杰克威胁taiga/被困循环中的不止2B还有她尼尔短篇小说过于平静的海洋解说.mkv",
"track": [
{
"@type": "General",
"Count": "348",
"StreamCount": "1",
"StreamKind": "General",
"StreamKind_String": "General",
"StreamKindID": "0",
"UniqueID": "170154106356885936877792612677801214602",
"UniqueID_String": "170154106356885936877792612677801214602 (0x80027D25E25DEDF30004DBC51064028A)",
"VideoCount": "1",
"AudioCount": "1",
"TextCount": "1",
"Video_Format_List": "HEVC",
"Video_Format_WithHint_List": "HEVC",
"Video_Codec_List": "HEVC",
"Audio_Format_List": "AAC LC",
"Audio_Format_WithHint_List": "AAC LC",
"Audio_Codec_List": "AAC LC",
"Text_Format_List": "ASS",
"Text_Format_WithHint_List": "ASS",
"Text_Codec_List": "ASS",
"CompleteName": "/mnt/e/Movies/bili/杰克威胁taiga/被困循环中的不止2B还有她尼尔短篇小说过于平静的海洋解说.mkv",
"FolderName": "/mnt/e/Movies/bili/杰克威胁taiga",
"FileNameExtension": "被困循环中的不止2B还有她尼尔短篇小说过于平静的海洋解说.mkv",
"FileName": "被困循环中的不止2B还有她尼尔短篇小说过于平静的海洋解说",
"FileExtension": "mkv",
"Format": "Matroska",
"Format_String": "Matroska",
"Format_Url": "https://matroska.org/downloads/windows.html",
"Format_Extensions": "mkv mk3d mka mks",
"Format_Commercial": "Matroska",
"Format_Version": "4",
"FileSize": "53489675",
"FileSize_String": "51.0 MiB",
"FileSize_String1": "51 MiB",
"FileSize_String2": "51 MiB",
"FileSize_String3": "51.0 MiB",
"FileSize_String4": "51.01 MiB",
"Duration": "495.130",
"Duration_String": "8 min 15 s",
"Duration_String1": "8 min 15 s 130 ms",
"Duration_String2": "8 min 15 s",
"Duration_String3": "00:08:15.130",
"Duration_String4": "00:08:04:21",
"Duration_String5": "00:08:15.130 (00:08:04:21)",
"OverallBitRate": "864253",
"OverallBitRate_String": "864 kb/s",
"FrameRate": "30.000",
"FrameRate_String": "30.000 FPS",
"FrameCount": "14541",
"IsStreamable": "Yes",
"Description": "Packed by Bilibili XCoder v2.0.2",
"File_Modified_Date": "2024-04-11 14:12:32 UTC",
"File_Modified_Date_Local": "2024-04-11 22:12:32",
"Encoded_Application": "Lavf60.16.100",
"Encoded_Application_String": "Lavf60.16.100",
"Encoded_Library": "Lavf60.16.100",
"Encoded_Library_String": "Lavf60.16.100",
"extra": {
"ErrorDetectionType": "Per level 1"
}
},
{
"@type": "Video",
"Count": "382",
"StreamCount": "1",
"StreamKind": "Video",
"StreamKind_String": "Video",
"StreamKindID": "0",
"StreamOrder": "0",
"ID": "1",
"ID_String": "1",
"UniqueID": "11908301149785012835",
"Format": "HEVC",
"Format_String": "HEVC",
"Format_Info": "High Efficiency Video Coding",
"Format_Url": "http://www.itu.int",
"Format_Commercial": "HEVC",
"Format_Profile": "Main",
"Format_Level": "4",
"Format_Tier": "Main",
"InternetMediaType": "video/H265",
"CodecID": "V_MPEGH/ISO/HEVC",
"Duration": "484.700000000",
"Duration_String": "8 min 4 s",
"Duration_String1": "8 min 4 s 700 ms",
"Duration_String2": "8 min 4 s",
"Duration_String3": "00:08:04.700",
"Duration_String4": "00:08:04:21",
"Duration_String5": "00:08:04.700 (00:08:04:21)",
"Width": "1440",
"Width_String": "1 440 pixels",
"Height": "1080",
"Height_String": "1 080 pixels",
"Sampled_Width": "1440",
"Sampled_Height": "1080",
"PixelAspectRatio": "1.333",
"DisplayAspectRatio": "1.778",
"DisplayAspectRatio_String": "16:9",
"FrameRate_Mode": "CFR",
"FrameRate_Mode_String": "Constant",
"FrameRate": "30.000",
"FrameRate_String": "30.000 FPS",
"FrameRate_Num": "30",
"FrameRate_Den": "1",
"FrameCount": "14541",
"ColorSpace": "YUV",
"ChromaSubsampling": "4:2:0",
"ChromaSubsampling_String": "4:2:0",
"BitDepth": "8",
"BitDepth_String": "8 bits",
"Delay": "0.000",
"Delay_String3": "00:00:00.000",
"Delay_String4": "00:00:00:00",
"Delay_String5": "00:00:00.000 (00:00:00:00)",
"Delay_Source": "Container",
"Delay_Source_String": "Container",
"Default": "Yes",
"Default_String": "Yes",
"Forced": "No",
"Forced_String": "No",
"colour_description_present": "Yes",
"colour_description_present_Source": "Container / Stream",
"colour_range": "Limited",
"colour_range_Source": "Container / Stream",
"colour_primaries": "BT.709",
"colour_primaries_Source": "Container / Stream",
"transfer_characteristics": "BT.709",
"transfer_characteristics_Source": "Container / Stream",
"matrix_coefficients": "BT.709",
"matrix_coefficients_Source": "Container / Stream",
"extra": {
"VENDOR_ID": "[0][0][0][0]"
}
},
{
"@type": "Audio",
"Count": "286",
"StreamCount": "1",
"StreamKind": "Audio",
"StreamKind_String": "Audio",
"StreamKindID": "0",
"StreamOrder": "1",
"ID": "2",
"ID_String": "2",
"UniqueID": "16022514981793959937",
"Format": "AAC",
"Format_String": "AAC LC",
"Format_Info": "Advanced Audio Codec Low Complexity",
"Format_Commercial": "AAC",
"Format_AdditionalFeatures": "LC",
"CodecID": "A_AAC-2",
"Duration": "484.778000000",
"Duration_String": "8 min 4 s",
"Duration_String1": "8 min 4 s 778 ms",
"Duration_String2": "8 min 4 s",
"Duration_String3": "00:08:04.778",
"Duration_String5": "00:08:04.778",
"Channels": "2",
"Channels_String": "2 channels",
"ChannelPositions": "Front: L R",
"ChannelPositions_String2": "2/0/0",
"ChannelLayout": "L R",
"SamplesPerFrame": "1024",
"SamplingRate": "48000",
"SamplingRate_String": "48.0 kHz",
"SamplingCount": "23269344",
"FrameRate": "46.875",
"FrameRate_String": "46.875 FPS (1024 SPF)",
"Compression_Mode": "Lossy",
"Compression_Mode_String": "Lossy",
"Delay": "0.000",
"Delay_String3": "00:00:00.000",
"Delay_String5": "00:00:00.000",
"Delay_Source": "Container",
"Delay_Source_String": "Container",
"Video_Delay": "0.000",
"Video_Delay_String3": "00:00:00.000",
"Video_Delay_String5": "00:00:00.000",
"Default": "Yes",
"Default_String": "Yes",
"Forced": "No",
"Forced_String": "No",
"extra": {
"VENDOR_ID": "[0][0][0][0]"
}
},
{
"@type": "Text",
"Count": "304",
"StreamCount": "1",
"StreamKind": "Text",
"StreamKind_String": "Text",
"StreamKindID": "0",
"StreamOrder": "2",
"ID": "3",
"ID_String": "3",
"UniqueID": "13702707746287918630",
"Format": "ASS",
"Format_String": "ASS",
"Format_Url": "http://ffdshow.sourceforge.net/tikiwiki/tiki-index.php?page=Getting+ffdshow",
"Format_Commercial": "ASS",
"CodecID": "S_TEXT/ASS",
"CodecID_Info": "Advanced Sub Station Alpha",
"Duration": "495.130000000",
"Duration_String": "8 min 15 s",
"Duration_String1": "8 min 15 s 130 ms",
"Duration_String2": "8 min 15 s",
"Duration_String3": "00:08:15.130",
"Duration_String5": "00:08:15.130",
"Compression_Mode": "Lossless",
"Compression_Mode_String": "Lossless",
"Encoded_Library": "Lavc60.31.102 ass",
"Encoded_Library_String": "Lavc60.31.102 ass",
"Default": "No",
"Default_String": "No",
"Forced": "No",
"Forced_String": "No"
}
]
}
}

